ntlm_bruteforce/__init__.py
ntlm_bruteforce/ntlm_bruteforce.py
ntlm_bruteforce-0.1.dist-info/METADATA
ntlm_bruteforce-0.1.dist-info/WHEEL
ntlm_bruteforce-0.1.dist-info/entry_points.txt
ntlm_bruteforce-0.1.dist-info/top_level.txt
ntlm_bruteforce-0.1.dist-info/RECORD
