Metadata-Version: 2.2
Name: ntlm_bruteforce
Version: 0.1
Summary: Librairie Python pour bruteforce NTLM hash
Home-page: https://github.com/noloxoyt/ntlm_bruteforce
Author: Noloxoyt
Author-email: noloxoyt@hotmail.com
Classifier: Programming Language :: Python :: 3
Classifier: License :: OSI Approved :: MIT License
Classifier: Operating System :: OS Independent
Requires-Python: >=3.6
Dynamic: author
Dynamic: author-email
Dynamic: classifier
Dynamic: description
Dynamic: description-content-type
Dynamic: home-page
Dynamic: requires-python
Dynamic: summary
